<?xml version="1.0" encoding="UTF-8"?>
<cinemas>
    <cinema name="Belarus">
        <film name="Avatar">
            <show date="5.04.2017 16:50">
                <row n="0">1 2 3 4 5 6 7 8 9 10 11</row>
                <row n="1">1 2 3 4 5 6 7 8 9 10 11</row>
                <row n="2">1 2 3 4 5 6 7 8 9 10 11</row>
                <row n="3">1 2 3 4 5 0 7 8 9 10 11</row>
                <row n="4">1 2 3 4 5 6 7 8 9 10 11</row>
                <row n="5">1 2 3 4 5 6 7 8 9 10 11</row>
                <row n="6">1 2 3 4 5 6 7 8 9 10 11</row>
                <row n="7">1 2 3 4 5 6 7 8 9 10 11</row>
                <row n="8">1 2 3 4 5 6 7 8 9 10 11</row>
                <row n="9">1 2 3 4 5 6 7 8 9 10 11</row>
            </show>
            <show date="5.04.2017 9:30">
                <row n="0">1 2 3 4 5 6 7 8 9 10 11</row>
                <row n="1">1 2 3 4 5 6 7 8 9 10 11</row>
                <row n="2">1 2 3 4 5 6 7 8 9 10 11</row>
                <row n="3">1 2 3 4 5 6 7 8 9 10 11</row>
                <row n="4">1 2 3 4 5 6 7 8 9 10 11</row>
                <row n="5">1 2 3 4 5 6 7 8 9 10 11</row>
                <row n="6">1 2 3 4 5 6 7 8 9 10 11</row>
                <row n="7">1 2 3 4 5 6 7 8 9 10 11</row>
                <row n="8">1 2 3 4 5 6 7 8 9 10 11</row>
                <row n="9">1 2 3 4 5 6 7 8 9 10 11</row>
            </show>
            <show date="4.04.2017 16:50">
                <row n="0">1 2 3 4 5 6 7 8 9 10 11</row>
                <row n="1">1 2 3 4 5 6 7 8 9 10 11</row>
                <row n="2">1 2 3 4 5 6 7 8 9 10 11</row>
                <row n="3">1 2 3 4 5 6 7 8 9 10 11</row>
                <row n="4">1 2 3 4 5 6 7 8 9 10 11</row>
                <row n="5">1 2 3 4 5 6 7 8 9 10 11</row>
                <row n="6">1 2 3 4 5 6 7 8 9 10 11</row>
                <row n="7">1 2 3 4 5 6 7 8 9 10 11</row>
                <row n="8">1 2 3 4 5 6 7 8 9 10 11</row>
                <row n="9">1 2 3 4 5 6 7 8 9 10 11</row>
            </show>
        </film>
        <film name="Godfather">
            <show date="5.04.2017 15:50">
                <row n="0">1 2 3 4 5 6 7 8 9 10 11</row>
                <row n="1">1 2 3 4 5 6 7 8 9 10 11</row>
                <row n="2">1 2 3 4 5 6 7 8 9 10 11</row>
                <row n="3">1 2 3 4 5 6 7 8 9 10 11</row>
                <row n="4">1 2 3 4 5 6 7 8 9 10 11</row>
                <row n="5">1 2 3 4 5 6 7 8 9 10 11</row>
                <row n="6">1 2 3 4 5 6 7 8 9 10 11</row>
                <row n="7">1 2 3 4 5 6 7 8 9 10 11</row>
                <row n="8">1 2 3 4 5 6 7 8 9 10 11</row>
                <row n="9">1 2 3 4 5 6 7 8 9 10 11</row>
            </show>
            <show date="6.04.2017 9:50">
                <row n="0">1 2 3 4 5 6 7 8 9 10 11</row>
                <row n="1">1 2 3 4 5 6 7 8 9 10 11</row>
                <row n="2">1 2 3 4 5 6 7 8 9 10 11</row>
                <row n="3">1 2 3 4 5 6 7 8 9 10 11</row>
                <row n="4">1 2 3 4 5 6 7 8 9 10 11</row>
                <row n="5">1 2 3 4 5 6 7 8 9 10 11</row>
                <row n="6">1 2 3 4 5 6 7 8 9 10 11</row>
                <row n="7">1 2 3 4 5 6 7 8 9 10 11</row>
                <row n="8">1 2 3 4 5 6 7 8 9 10 11</row>
                <row n="9">1 2 3 4 5 6 7 8 9 10 11</row>
            </show>
            <show date="5.04.2017 9:50">
                <row n="0">1 2 3 4 5 6 7 8 9 10 11</row>
                <row n="1">1 2 3 4 5 6 7 8 9 10 11</row>
                <row n="2">1 2 3 4 5 6 7 8 9 10 11</row>
                <row n="3">1 2 3 4 5 6 7 8 9 10 11</row>
                <row n="4">1 2 3 4 5 6 7 8 9 10 11</row>
                <row n="5">1 2 3 4 5 6 7 8 9 10 11</row>
                <row n="6">1 2 3 4 5 6 7 8 9 10 11</row>
                <row n="7">1 2 3 4 5 6 7 8 9 10 11</row>
                <row n="8">1 2 3 4 5 6 7 8 9 10 11</row>
                <row n="9">1 2 3 4 5 6 7 8 9 10 11</row>
            </show>
        </film>
        <film name="Terminator 6">
            <show date="7.04.2017 16:50">
                <row n="0">1 2 3 4 5 6 7 8 9 10 11</row>
                <row n="1">1 2 3 4 5 6 7 8 9 10 11</row>
                <row n="2">1 2 3 4 5 6 7 8 9 10 11</row>
                <row n="3">1 2 3 4 5 6 7 8 9 10 11</row>
                <row n="4">1 2 3 4 5 6 7 8 9 10 11</row>
                <row n="5">1 2 3 4 5 6 7 8 9 10 11</row>
                <row n="6">1 2 3 4 5 6 7 8 9 10 11</row>
                <row n="7">1 2 3 4 5 6 7 8 9 10 11</row>
                <row n="8">1 2 3 4 5 6 7 8 9 10 11</row>
                <row n="9">1 2 3 4 5 6 7 8 9 10 11</row>
            </show>
            <show date="8.04.2017 16:50">
                <row n="0">1 2 3 4 5 6 7 8 9 10 11</row>
                <row n="1">1 2 3 4 5 6 7 8 9 10 11</row>
                <row n="2">1 2 3 4 5 6 7 8 9 10 11</row>
                <row n="3">1 2 3 4 5 6 7 8 9 10 11</row>
                <row n="4">1 2 3 4 5 6 7 8 9 10 11</row>
                <row n="5">1 2 3 4 5 6 7 8 9 10 11</row>
                <row n="6">1 2 3 4 5 6 7 8 9 10 11</row>
                <row n="7">1 2 3 4 5 6 7 8 9 10 11</row>
                <row n="8">1 2 3 4 5 6 7 8 9 10 11</row>
                <row n="9">1 2 3 4 5 6 7 8 9 10 11</row>
            </show>
            <show date="9.04.2017 16:50">
                <row n="0">1 2 3 4 5 6 7 8 9 10 11</row>
                <row n="1">1 2 3 4 5 6 7 8 9 10 11</row>
                <row n="2">1 2 3 4 5 6 7 8 9 10 11</row>
                <row n="3">1 2 3 4 5 6 7 8 9 10 11</row>
                <row n="4">1 2 3 4 5 6 7 8 9 10 11</row>
                <row n="5">1 2 3 4 5 6 7 8 9 10 11</row>
                <row n="6">1 2 3 4 5 6 7 8 9 10 11</row>
                <row n="7">1 2 3 4 5 6 7 8 9 10 11</row>
                <row n="8">1 2 3 4 5 6 7 8 9 10 11</row>
                <row n="9">1 2 3 4 5 6 7 8 9 10 11</row>
            </show>
        </film>
    </cinema>
    <cinema name="Avrora">
        <film name="Avatar">
            <show date="7.04.2017 16:50">
                <row n="0">1 2 3 4 5 6 7 8 9 10 11</row>
                <row n="1">1 2 3 4 5 6 7 8 9 10 11</row>
                <row n="2">1 2 3 4 5 6 7 8 9 10 11</row>
                <row n="3">1 2 3 4 5 6 7 8 9 10 11</row>
                <row n="4">1 2 3 4 5 6 7 8 9 10 11</row>
                <row n="5">1 2 3 4 5 6 7 8 9 10 11</row>
                <row n="6">1 2 3 4 5 6 7 8 9 10 11</row>
                <row n="7">1 2 3 4 5 6 7 8 9 10 11</row>
                <row n="8">1 2 3 4 5 6 7 8 9 10 11</row>
                <row n="9">1 2 3 4 5 6 7 8 9 10 11</row>
            </show>
            <show date="8.04.2017 9:30">
                <row n="0">1 2 3 4 5 6 7 8 9 10 11</row>
                <row n="1">1 2 3 4 5 6 7 8 9 10 11</row>
                <row n="2">1 2 3 4 5 6 7 8 9 10 11</row>
                <row n="3">1 2 3 4 5 6 7 8 9 10 11</row>
                <row n="4">1 2 3 4 5 6 7 8 9 10 11</row>
                <row n="5">1 2 3 4 5 6 7 8 9 10 11</row>
                <row n="6">1 2 3 4 5 6 7 8 9 10 11</row>
                <row n="7">1 2 3 4 5 6 7 8 9 10 11</row>
                <row n="8">1 2 3 4 5 6 7 8 9 10 11</row>
                <row n="9">1 2 3 4 5 6 7 8 9 10 11</row>
            </show>
            <show date="8.04.2017 16:50">
                <row n="0">1 2 3 4 5 6 7 8 9 10 11</row>
                <row n="1">1 2 3 4 5 6 7 8 9 10 11</row>
                <row n="2">1 2 3 4 5 6 7 8 9 10 11</row>
                <row n="3">1 2 3 4 5 6 7 8 9 10 11</row>
                <row n="4">1 2 3 4 5 6 7 8 9 10 11</row>
                <row n="5">1 2 3 4 5 6 7 8 9 10 11</row>
                <row n="6">1 2 3 4 5 6 7 8 9 10 11</row>
                <row n="7">1 2 3 4 5 6 7 8 9 10 11</row>
                <row n="8">1 2 3 4 5 6 7 8 9 10 11</row>
                <row n="9">1 2 3 4 5 6 7 8 9 10 11</row>
            </show>
        </film>
        <film name="Godfather">
            <show date="5.04.2017 15:50">
                <row n="0">1 2 3 4 5 6 7 8 9 10 11</row>
                <row n="1">1 2 3 4 5 6 7 8 9 10 11</row>
                <row n="2">1 2 3 4 5 6 7 8 9 10 11</row>
                <row n="3">1 2 3 4 5 6 7 8 9 10 11</row>
                <row n="4">1 2 3 4 5 6 7 8 9 10 11</row>
                <row n="5">1 2 3 4 5 6 7 8 9 10 11</row>
                <row n="6">1 2 3 4 5 6 7 8 9 10 11</row>
                <row n="7">1 2 3 4 5 6 7 8 9 10 11</row>
                <row n="8">1 2 3 4 5 6 7 8 9 10 11</row>
                <row n="9">1 2 3 4 5 6 7 8 9 10 11</row>
            </show>
            <show date="6.04.2017 9:50">
                <row n="0">1 2 3 4 5 6 7 8 9 10 11</row>
                <row n="1">1 2 3 4 5 6 7 8 9 10 11</row>
                <row n="2">1 2 3 4 5 6 7 8 9 10 11</row>
                <row n="3">1 2 3 4 5 6 7 8 9 10 11</row>
                <row n="4">1 2 3 4 5 6 7 8 9 10 11</row>
                <row n="5">1 2 3 4 5 6 7 8 9 10 11</row>
                <row n="6">1 2 3 4 5 6 7 8 9 10 11</row>
                <row n="7">1 2 3 4 5 6 7 8 9 10 11</row>
                <row n="8">1 2 3 4 5 6 7 8 9 10 11</row>
                <row n="9">1 2 3 4 5 6 7 8 9 10 11</row>
            </show>
            <show date="5.04.2017 9:50">
                <row n="0">1 2 3 4 5 6 7 8 9 10 11</row>
                <row n="1">1 2 3 4 5 6 7 8 9 10 11</row>
                <row n="2">1 2 3 4 5 6 7 8 9 10 11</row>
                <row n="3">1 2 3 4 5 6 7 8 9 10 11</row>
                <row n="4">1 2 3 4 5 6 7 8 9 10 11</row>
                <row n="5">1 2 3 4 5 6 7 8 9 10 11</row>
                <row n="6">1 2 3 4 5 6 7 8 9 10 11</row>
                <row n="7">1 2 3 4 5 6 7 8 9 10 11</row>
                <row n="8">1 2 3 4 5 6 7 8 9 10 11</row>
                <row n="9">1 2 3 4 5 6 7 8 9 10 11</row>
            </show>
        </film>
        <film name="Fast and Furious 17">
            <show date="7.04.2017 16:50">
                <row n="0">1 2 3 4 5 6 7 8 9 10 11</row>
                <row n="1">1 2 3 4 5 6 7 8 9 10 11</row>
                <row n="2">1 2 3 4 5 6 7 8 9 10 11</row>
                <row n="3">1 2 3 4 5 6 7 8 9 10 11</row>
                <row n="4">1 2 3 4 5 6 7 8 9 10 11</row>
                <row n="5">1 2 3 4 5 6 7 8 9 10 11</row>
                <row n="6">1 2 3 4 5 6 7 8 9 10 11</row>
                <row n="7">1 2 3 4 5 6 7 8 9 10 11</row>
                <row n="8">1 2 3 4 5 6 7 8 9 10 11</row>
                <row n="9">1 2 3 4 5 6 7 8 9 10 11</row>
            </show>
            <show date="8.04.2017 16:50">
                <row n="0">1 2 3 4 5 6 7 8 9 10 11</row>
                <row n="1">1 2 3 4 5 6 7 8 9 10 11</row>
                <row n="2">1 2 3 4 5 6 7 8 9 10 11</row>
                <row n="3">1 2 3 4 5 6 7 8 9 10 11</row>
                <row n="4">1 2 3 4 5 6 7 8 9 10 11</row>
                <row n="5">1 2 3 4 5 6 7 8 9 10 11</row>
                <row n="6">1 2 3 4 5 6 7 8 9 10 11</row>
                <row n="7">1 2 3 4 5 6 7 8 9 10 11</row>
                <row n="8">1 2 3 4 5 6 7 8 9 10 11</row>
                <row n="9">1 2 3 4 5 6 7 8 9 10 11</row>
            </show>
            <show date="9.04.2017 16:50">
                <row n="0">1 2 3 4 5 6 7 8 9 10 11</row>
                <row n="1">1 2 3 4 5 6 7 8 9 10 11</row>
                <row n="2">1 2 3 4 5 6 7 8 9 10 11</row>
                <row n="3">1 2 3 4 5 6 7 8 9 10 11</row>
                <row n="4">1 2 3 4 5 6 7 8 9 10 11</row>
                <row n="5">1 2 3 4 5 6 7 8 9 10 11</row>
                <row n="6">1 2 3 4 5 6 7 8 9 10 11</row>
                <row n="7">1 2 3 4 5 6 7 8 9 10 11</row>
                <row n="8">1 2 3 4 5 6 7 8 9 10 11</row>
                <row n="9">1 2 3 4 5 6 7 8 9 10 11</row>
            </show>
        </film>
    </cinema>
    <cinema name="Kiev">
        <film name="Robocop">
            <show date="5.04.2017 16:40">
                <row n="0">1 2 3 4 5 6 7 8 9 10 11</row>
                <row n="1">1 2 3 4 5 6 7 8 9 10 11</row>
                <row n="2">1 2 3 4 5 6 7 8 9 10 11</row>
                <row n="3">1 2 3 4 5 6 7 8 9 10 11</row>
                <row n="4">1 2 3 4 5 6 7 8 9 10 11</row>
                <row n="5">1 2 3 4 5 6 7 8 9 10 11</row>
                <row n="6">1 2 3 4 5 6 7 8 9 10 11</row>
                <row n="7">1 2 3 4 5 6 7 8 9 10 11</row>
                <row n="8">1 2 3 4 5 6 7 8 9 10 11</row>
                <row n="9">1 2 3 4 5 6 7 8 9 10 11</row>
            </show>
            <show date="5.04.2017 9:20">
                <row n="0">1 2 3 4 5 6 7 8 9 10 11</row>
                <row n="1">1 2 3 4 5 6 7 8 9 10 11</row>
                <row n="2">1 2 3 4 5 6 7 8 9 10 11</row>
                <row n="3">1 2 3 4 5 6 7 8 9 10 11</row>
                <row n="4">1 2 3 4 5 6 7 8 9 10 11</row>
                <row n="5">1 2 3 4 5 6 7 8 9 10 11</row>
                <row n="6">1 2 3 4 5 6 7 8 9 10 11</row>
                <row n="7">1 2 3 4 5 6 7 8 9 10 11</row>
                <row n="8">1 2 3 4 5 6 7 8 9 10 11</row>
                <row n="9">1 2 3 4 5 6 7 8 9 10 11</row>
            </show>
            <show date="4.04.2017 16:40">
                <row n="0">1 2 3 4 5 6 7 8 9 10 11</row>
                <row n="1">1 2 3 4 5 6 7 8 9 10 11</row>
                <row n="2">1 2 3 4 5 6 7 8 9 10 11</row>
                <row n="3">1 2 3 4 5 6 7 8 9 10 11</row>
                <row n="4">1 2 3 4 5 6 7 8 9 10 11</row>
                <row n="5">1 2 3 4 5 6 7 8 9 10 11</row>
                <row n="6">1 2 3 4 5 6 7 8 9 10 11</row>
                <row n="7">1 2 3 4 5 6 7 8 9 10 11</row>
                <row n="8">1 2 3 4 5 6 7 8 9 10 11</row>
                <row n="9">1 2 3 4 5 6 7 8 9 10 11</row>
            </show>
        </film>
        <film name="Godfather">
            <show date="5.04.2017 15:50">
                <row n="0">1 2 3 4 5 6 7 8 9 10 11</row>
                <row n="1">1 2 3 4 5 6 7 8 9 10 11</row>
                <row n="2">1 2 3 4 5 6 7 8 9 10 11</row>
                <row n="3">1 2 3 4 5 6 7 8 9 10 11</row>
                <row n="4">1 2 3 4 5 6 7 8 9 10 11</row>
                <row n="5">1 2 3 4 5 6 7 8 9 10 11</row>
                <row n="6">1 2 3 4 5 6 7 8 9 10 11</row>
                <row n="7">1 2 3 4 5 6 7 8 9 10 11</row>
                <row n="8">1 2 3 4 5 6 7 8 9 10 11</row>
                <row n="9">1 2 3 4 5 6 7 8 9 10 11</row>
            </show>
            <show date="6.04.2017 9:50">
                <row n="0">1 2 3 4 5 6 7 8 9 10 11</row>
                <row n="1">1 2 3 4 5 6 7 8 9 10 11</row>
                <row n="2">1 2 3 4 5 6 7 8 9 10 11</row>
                <row n="3">1 2 3 4 5 6 7 8 9 10 11</row>
                <row n="4">1 2 3 4 5 6 7 8 9 10 11</row>
                <row n="5">1 2 3 4 5 6 7 8 9 10 11</row>
                <row n="6">1 2 3 4 5 6 7 8 9 10 11</row>
                <row n="7">1 2 3 4 5 6 7 8 9 10 11</row>
                <row n="8">1 2 3 4 5 6 7 8 9 10 11</row>
                <row n="9">1 2 3 4 5 6 7 8 9 10 11</row>
            </show>
            <show date="5.04.2017 9:50">
                <row n="0">1 2 3 4 5 6 7 8 9 10 11</row>
                <row n="1">1 2 3 4 5 6 7 8 9 10 11</row>
                <row n="2">1 2 3 4 5 6 7 8 9 10 11</row>
                <row n="3">1 2 3 4 5 6 7 8 9 10 11</row>
                <row n="4">1 2 3 4 5 6 7 8 9 10 11</row>
                <row n="5">1 2 3 4 5 6 7 8 9 10 11</row>
                <row n="6">1 2 3 4 5 6 7 8 9 10 11</row>
                <row n="7">1 2 3 4 5 6 7 8 9 10 11</row>
                <row n="8">1 2 3 4 5 6 7 8 9 10 11</row>
                <row n="9">1 2 3 4 5 6 7 8 9 10 11</row>
            </show>
        </film>
        <film name="Fast and Furious 17">
            <show date="7.04.2017 16:50">
                <row n="0">1 2 3 4 5 6 7 8 9 10 11</row>
                <row n="1">1 2 3 4 5 6 7 8 9 10 11</row>
                <row n="2">1 2 3 4 5 6 7 8 9 10 11</row>
                <row n="3">1 2 3 4 5 6 7 8 9 10 11</row>
                <row n="4">1 2 3 4 5 6 7 8 9 10 11</row>
                <row n="5">1 2 3 4 5 6 7 8 9 10 11</row>
                <row n="6">1 2 3 4 5 6 7 8 9 10 11</row>
                <row n="7">1 2 3 4 5 6 7 8 9 10 11</row>
                <row n="8">1 2 3 4 5 6 7 8 9 10 11</row>
                <row n="9">1 2 3 4 5 6 7 8 9 10 11</row>
            </show>
            <show date="8.04.2017 16:50">
                <row n="0">1 2 3 4 5 6 7 8 9 10 11</row>
                <row n="1">1 2 3 4 5 6 7 8 9 10 11</row>
                <row n="2">1 2 3 4 5 6 7 8 9 10 11</row>
                <row n="3">1 2 3 4 5 6 7 8 9 10 11</row>
                <row n="4">1 2 3 4 5 6 7 8 9 10 11</row>
                <row n="5">1 2 3 4 5 6 7 8 9 10 11</row>
                <row n="6">1 2 3 4 5 6 7 8 9 10 11</row>
                <row n="7">1 2 3 4 5 6 7 8 9 10 11</row>
                <row n="8">1 2 3 4 5 6 7 8 9 10 11</row>
                <row n="9">1 2 3 4 5 6 7 8 9 10 11</row>
            </show>
            <show date="9.04.2017 16:50">
                <row n="0">1 2 3 4 5 6 7 8 9 10 11</row>
                <row n="1">1 2 3 4 5 6 7 8 9 10 11</row>
                <row n="2">1 2 3 4 5 6 7 8 9 10 11</row>
                <row n="3">1 2 3 4 5 6 7 8 9 10 11</row>
                <row n="4">1 2 3 4 5 6 7 8 9 10 11</row>
                <row n="5">1 2 3 4 5 6 7 8 9 10 11</row>
                <row n="6">1 2 3 4 5 6 7 8 9 10 11</row>
                <row n="7">1 2 3 4 5 6 7 8 9 10 11</row>
                <row n="8">1 2 3 4 5 6 7 8 9 10 11</row>
                <row n="9">1 2 3 4 5 6 7 8 9 10 11</row>
            </show>
        </film>
    </cinema>
</cinemas>